pytest_snob/__init__.py
pytest_snob/plugin.py
pytest_snob-0.1.14.dist-info/METADATA
pytest_snob-0.1.14.dist-info/WHEEL
pytest_snob-0.1.14.dist-info/entry_points.txt
pytest_snob-0.1.14.dist-info/top_level.txt
pytest_snob-0.1.14.dist-info/RECORD
